[
  {
    "componentKind": "setComponent",
    "id": "header",
    "name": "ヘッダー",
    "logo": ""
  },
  {
    "componentKind": "setComponent",
    "id": "mainArea",
    "name": "メインエリア",
    "title": { "align": "1", "context": "少人数個別コースが強い" },
    "text": {
      "align": "1",
      "context": "お子様の学習度に合わせ講師が最適なカリキュラムをご提案します。"
    },
    "textColor": "4",
    "backgroundImage": "https://images.@@images-domain@@/web-assets/common/web/11/34557214_20220309.png",
    "buttons": [{ "text": "お問い合わせ", "link": "", "linkType": 1 }]
  },
  {
    "componentKind": "setComponent",
    "id": "oneLineNews",
    "name": "ワンラインニュース",
    "date": "2022/04/01",
    "title": "Webサイトをリニューアルしました",
    "label": "お知らせ",
    "link": ""
  },
  {
    "componentKind": "setComponent",
    "id": "textWithLeftAndRightImages",
    "name": "左右画像付きテキスト",
    "heading": "●●●学習塾について",
    "layoutType": "1",
    "images": [
      {
        "title": "●●●学習塾の特徴を一言で入力します。",
        "text": "●●●学習塾の特徴の詳細を入力します。●●●学習塾の特徴の詳細を入力します。●●●学習塾の特徴の詳細を入力します。",
        "image": "https://images.@@images-domain@@/web-assets/common/web/11/49466209_20220309.png",
        "imageName": "",
        "imageAlign": "1",
        "link": ""
      }
    ]
  },
  {
    "componentKind": "singleComponent",
    "id": "heading2",
    "name": "見出し2",
    "context": "コース紹介",
    "align": "1",
    "link": "",
    "spaceInfo": {
      "spaceKind": "1",
      "space": "1",
      "topSpace": "1",
      "bottomSpace": "1",
      "leftSpace": "1",
      "rightSpace": "1"
    }
  },
  {
    "componentKind": "layoutComponent",
    "id": "layout-4",
    "name": "4列",
    "checkSameHeader": false,
    "spaceInfo": {
      "spaceKind": "1",
      "space": "1",
      "topSpace": "1",
      "bottomSpace": "1",
      "leftSpace": "1",
      "rightSpace": "1"
    },
    "layoutNum": 4,
    "layoutType": "1",
    "componentList": [
      [
        {
          "componentKind": "singleComponent",
          "id": "image",
          "name": "画像",
          "image": "https://images.@@images-domain@@/web-assets/common/web/11/53634176_20220309.png",
          "imageName": "",
          "align": "1",
          "alternateText": "",
          "width": "",
          "height": "",
          "link": "",
          "spaceInfo": {
            "spaceKind": "1",
            "space": "1",
            "topSpace": "1",
            "bottomSpace": "1",
            "leftSpace": "1",
            "rightSpace": "1"
          }
        },
        {
          "componentKind": "singleComponent",
          "id": "heading3",
          "name": "見出し3",
          "context": "小学生コース",
          "align": "1",
          "link": "",
          "spaceInfo": {
            "spaceKind": "1",
            "space": "1",
            "topSpace": "1",
            "bottomSpace": "1",
            "leftSpace": "1",
            "rightSpace": "1"
          }
        },
        {
          "componentKind": "singleComponent",
          "id": "text",
          "name": "テキスト",
          "context": "小学生コースの紹介文を入力します。",
          "align": "1",
          "link": "",
          "spaceInfo": {
            "spaceKind": "1",
            "space": "1",
            "topSpace": "1",
            "bottomSpace": "1",
            "leftSpace": "1",
            "rightSpace": "1"
          }
        },
        {
          "componentKind": "singleComponent",
          "id": "button",
          "name": "ボタン",
          "kind": "2",
          "width": "224",
          "height": "56",
          "align": "1",
          "text": "詳しくはこちら",
          "link": "",
          "spaceInfo": {
            "spaceKind": "1",
            "space": "1",
            "topSpace": "1",
            "bottomSpace": "1",
            "leftSpace": "1",
            "rightSpace": "1"
          }
        }
      ],
      [
        {
          "componentKind": "singleComponent",
          "id": "image",
          "name": "画像",
          "image": "https://images.@@images-domain@@/web-assets/common/web/11/53634176_20220309.png",
          "imageName": "",
          "align": "1",
          "alternateText": "",
          "width": "",
          "height": "",
          "link": "",
          "spaceInfo": {
            "spaceKind": "1",
            "space": "1",
            "topSpace": "1",
            "bottomSpace": "1",
            "leftSpace": "1",
            "rightSpace": "1"
          }
        },
        {
          "componentKind": "singleComponent",
          "id": "heading3",
          "name": "見出し3",
          "context": "中学生コース",
          "align": "1",
          "link": "",
          "spaceInfo": {
            "spaceKind": "1",
            "space": "1",
            "topSpace": "1",
            "bottomSpace": "1",
            "leftSpace": "1",
            "rightSpace": "1"
          }
        },
        {
          "componentKind": "singleComponent",
          "id": "text",
          "name": "テキスト",
          "context": "中学生コースの紹介文を入力します。",
          "align": "1",
          "link": "",
          "spaceInfo": {
            "spaceKind": "1",
            "space": "1",
            "topSpace": "1",
            "bottomSpace": "1",
            "leftSpace": "1",
            "rightSpace": "1"
          }
        },
        {
          "componentKind": "singleComponent",
          "id": "button",
          "name": "ボタン",
          "kind": "2",
          "width": "224",
          "height": "56",
          "align": "1",
          "text": "詳しくはこちら",
          "link": "",
          "spaceInfo": {
            "spaceKind": "1",
            "space": "1",
            "topSpace": "1",
            "bottomSpace": "1",
            "leftSpace": "1",
            "rightSpace": "1"
          }
        }
      ],
      [
        {
          "componentKind": "singleComponent",
          "id": "image",
          "name": "画像",
          "image": "https://images.@@images-domain@@/web-assets/common/web/11/53634176_20220309.png",
          "imageName": "",
          "align": "1",
          "alternateText": "",
          "width": "",
          "height": "",
          "link": "",
          "spaceInfo": {
            "spaceKind": "1",
            "space": "1",
            "topSpace": "1",
            "bottomSpace": "1",
            "leftSpace": "1",
            "rightSpace": "1"
          }
        },
        {
          "componentKind": "singleComponent",
          "id": "heading3",
          "name": "見出し3",
          "context": "高校生コース",
          "align": "1",
          "link": "",
          "spaceInfo": {
            "spaceKind": "1",
            "space": "1",
            "topSpace": "1",
            "bottomSpace": "1",
            "leftSpace": "1",
            "rightSpace": "1"
          }
        },
        {
          "componentKind": "singleComponent",
          "id": "text",
          "name": "テキスト",
          "context": "高校生コースの紹介文を入力します。",
          "align": "1",
          "link": "",
          "spaceInfo": {
            "spaceKind": "1",
            "space": "1",
            "topSpace": "1",
            "bottomSpace": "1",
            "leftSpace": "1",
            "rightSpace": "1"
          }
        },
        {
          "componentKind": "singleComponent",
          "id": "button",
          "name": "ボタン",
          "kind": "2",
          "width": "224",
          "height": "56",
          "align": "1",
          "text": "詳しくはこちら",
          "link": "",
          "spaceInfo": {
            "spaceKind": "1",
            "space": "1",
            "topSpace": "1",
            "bottomSpace": "1",
            "leftSpace": "1",
            "rightSpace": "1"
          }
        }
      ],
      [
        {
          "componentKind": "singleComponent",
          "id": "image",
          "name": "画像",
          "image": "https://images.@@images-domain@@/web-assets/common/web/11/53634176_20220309.png",
          "imageName": "",
          "align": "1",
          "alternateText": "",
          "width": "",
          "height": "",
          "link": "",
          "spaceInfo": {
            "spaceKind": "1",
            "space": "1",
            "topSpace": "1",
            "bottomSpace": "1",
            "leftSpace": "1",
            "rightSpace": "1"
          }
        },
        {
          "componentKind": "singleComponent",
          "id": "heading3",
          "name": "見出し3",
          "context": "高卒生コース",
          "align": "1",
          "link": "",
          "spaceInfo": {
            "spaceKind": "1",
            "space": "1",
            "topSpace": "1",
            "bottomSpace": "1",
            "leftSpace": "1",
            "rightSpace": "1"
          }
        },
        {
          "componentKind": "singleComponent",
          "id": "text",
          "name": "テキスト",
          "context": "高卒生コースの紹介文を入力します。",
          "align": "1",
          "link": "",
          "spaceInfo": {
            "spaceKind": "1",
            "space": "1",
            "topSpace": "1",
            "bottomSpace": "1",
            "leftSpace": "1",
            "rightSpace": "1"
          }
        },
        {
          "componentKind": "singleComponent",
          "id": "button",
          "name": "ボタン",
          "kind": "2",
          "width": "224",
          "height": "56",
          "align": "1",
          "text": "詳しくはこちら",
          "link": "",
          "spaceInfo": {
            "spaceKind": "1",
            "space": "1",
            "topSpace": "1",
            "bottomSpace": "1",
            "leftSpace": "1",
            "rightSpace": "1"
          }
        }
      ]
    ]
  },
  {
    "componentKind": "setComponent",
    "id": "textWithLeftAndRightImages",
    "name": "左右画像付きテキスト",
    "heading": "●●●学習塾が選ばれる理由",
    "layoutType": "1",
    "images": [
      {
        "title": "「まなぶ楽しさ」からスタートします。",
        "text": "お子さまの学習意欲は目標までの長い道のりを走り続けるうえで何よりのモチベーションとなります。●●●学習塾ではまず最初にまなぶ楽しさを実感いただくカリキュラムから始め、学力を育むことを追及しています。",
        "image": "https://images.@@images-domain@@/web-assets/common/web/11/28035220_20220309.png",
        "imageName": "",
        "imageAlign": "1",
        "link": ""
      }
    ]
  },
  {
    "componentKind": "setComponent",
    "id": "customerVoice",
    "name": "お客さまの声",
    "heading": { "align": "1", "context": "お客様の声" },
    "layoutDirection": "1",
    "layoutType": "1",
    "contents": [
      {
        "title": "お客様の声タイトルを入力します",
        "text": "卒業いただいたお客様の声を入力します。",
        "image": "",
        "link": ""
      },
      {
        "title": "お客様の声タイトルを入力します",
        "text": "卒業いただいたお客様の声を入力します。",
        "image": "",
        "link": ""
      },
      {
        "title": "お客様の声タイトルを入力します",
        "text": "卒業いただいたお客様の声を入力します。",
        "image": "",
        "link": ""
      },
      {
        "title": "お客様の声タイトルを入力します",
        "text": "卒業いただいたお客様の声を入力します。",
        "image": "",
        "imageName": "",
        "imageAlign": "1",
        "link": ""
      }
    ]
  },
  {
    "componentKind": "singleComponent",
    "id": "heading2",
    "name": "見出し2",
    "context": "お問い合わせ",
    "align": "1",
    "link": "",
    "spaceInfo": {
      "spaceKind": "1",
      "space": "1",
      "topSpace": "1",
      "bottomSpace": "1",
      "leftSpace": "1",
      "rightSpace": "1"
    }
  },
  {
    "componentKind": "formComponent",
    "id": "",
    "name": "",
    "previewSrc": ""
  },
  {
    "componentKind": "singleComponent",
    "id": "heading2",
    "name": "見出し2",
    "context": "私たちについて",
    "align": "1",
    "link": "",
    "spaceInfo": {
      "spaceKind": "1",
      "space": "1",
      "topSpace": "1",
      "bottomSpace": "1",
      "leftSpace": "1",
      "rightSpace": "1"
    }
  },
  {
    "componentKind": "layoutComponent",
    "id": "layout-2",
    "name": "2列",
    "checkSameHeader": false,
    "spaceInfo": {
      "spaceKind": "1",
      "space": "1",
      "topSpace": "1",
      "bottomSpace": "1",
      "leftSpace": "1",
      "rightSpace": "1"
    },
    "layoutNum": 2,
    "layoutType": "1",
    "componentList": [
      [
        {
          "componentKind": "singleComponent",
          "id": "text",
          "name": "テキスト",
          "context": "<iframe src=\\"https://www.google.com/maps/embed?pb=!1m14!1m12!1m3!1d51851.69908212983!2d139.78310180000003!3d35.6836203!2m3!1f0!2f0!3f0!3m2!1i1024!2i768!4f13.1!5e0!3m2!1sja!2sjp!4v1637540484748!5m2!1sja!2sjp\\" width=\\"500\\" height=\\"450\\" style=\\"border:0;\\" allowfullscreen=\\"\\" loading=\\"lazy\\"></iframe>",
          "align": "1",
          "link": "",
          "spaceInfo": {
            "spaceKind": "1",
            "space": "1",
            "topSpace": "1",
            "bottomSpace": "1",
            "leftSpace": "1",
            "rightSpace": "1"
          }
        }
      ],
      [
        {
          "componentKind": "singleComponent",
          "id": "heading3",
          "name": "見出し3",
          "context": "企業情報",
          "align": "1",
          "link": "",
          "spaceInfo": {
            "spaceKind": "1",
            "space": "1",
            "topSpace": "1",
            "bottomSpace": "1",
            "leftSpace": "1",
            "rightSpace": "1"
          }
        },
        {
          "componentKind": "singleComponent",
          "id": "text",
          "name": "テキスト",
          "context": "100-0000\\n東京都港区*************\\n\\n03-****-****\\ninfo@********.com",
          "align": "1",
          "link": "",
          "spaceInfo": {
            "spaceKind": "1",
            "space": "1",
            "topSpace": "1",
            "bottomSpace": "1",
            "leftSpace": "1",
            "rightSpace": "1"
          }
        }
      ]
    ]
  },
  {
    "componentKind": "setComponent",
    "id": "footer",
    "name": "フッター"
  }
]
